README.rst
setup.cfg
setup.py
ldappy/__init__.py
ldappy/config.py
ldappy/connection.py
ldappy/dotexdict.py
ldappy/group.py
ldappy/groups.py
ldappy/ldapconnection.py
ldappy/ldapobject.py
ldappy/ldappy.py
ldappy/ldapquery.py
ldappy/safeldap.py
ldappy/user.py
ldappy/users.py
ldappy.egg-info/PKG-INFO
ldappy.egg-info/SOURCES.txt
ldappy.egg-info/dependency_links.txt
ldappy.egg-info/requires.txt
ldappy.egg-info/top_level.txt