Metadata-Version: 1.1
Name: ldappy
Version: 0.1.5
Summary: Query LDAP server without LDAP knowledge
Home-page: https://github.com/dusking/ldapy
Author: Omer Duskin
Author-email: dusking@gmail.com
License: LICENSE
Platform: All
Classifier: Programming Language :: Python
Classifier: Natural Language :: English
Classifier: Environment :: Console
Classifier: Intended Audience :: Developers
Classifier: Intended Audience :: Information Technology
Classifier: Intended Audience :: System Administrators
Classifier: License :: OSI Approved :: Apache Software License
Classifier: Operating System :: POSIX :: Linux
Classifier: Operating System :: Microsoft
Classifier: Topic :: Software Development :: Libraries :: Python Modules
